simfire/__init__.py
simfire/enums.py
simfire/game/__init__.py
simfire/game/_tests/__init__.py
simfire/game/_tests/test_game.py
simfire/game/_tests/test_sprites.py
simfire/game/game.py
simfire/game/image.py
simfire/game/managers/__init__.py
simfire/game/managers/_tests/__init__.py
simfire/game/managers/_tests/test_fire.py
simfire/game/managers/_tests/test_mitigation.py
simfire/game/managers/fire.py
simfire/game/managers/mitigation.py
simfire/game/sprites.py
simfire/sim/__init__.py
simfire/sim/_tests/__init__.py
simfire/sim/_tests/test_simulation.py
simfire/sim/simulation.py
simfire/utils/__init__.py
simfire/utils/_tests/__init__.py
simfire/utils/_tests/test_config.py
simfire/utils/_tests/test_configs/test_config.yml
simfire/utils/_tests/test_configs/test_config_bad.yml
simfire/utils/_tests/test_configs/test_config_flat_simple.yml
simfire/utils/_tests/test_configs/test_config_gaussian.yml
simfire/utils/_tests/test_configs/test_config_rothermel_manager.yml
simfire/utils/_tests/test_graph.py
simfire/utils/_tests/test_layers.py
simfire/utils/_tests/test_log.py
simfire/utils/_tests/test_terrain.py
simfire/utils/_tests/test_units.py
simfire/utils/assets/__init__.py
simfire/utils/assets/fireline_logo.png
simfire/utils/config.py
simfire/utils/decorators.py
simfire/utils/generate_cfd_wind_layer.py
simfire/utils/graph.py
simfire/utils/layers.py
simfire/utils/log.py
simfire/utils/pregenerated_wind_files/generated_wind_directions.npy
simfire/utils/pregenerated_wind_files/generated_wind_magnitudes.npy
simfire/utils/terrain.py
simfire/utils/textures/__init__.py
simfire/utils/textures/terrain.jpg
simfire/utils/units.py
simfire/world/__init__.py
simfire/world/_tests/__init__.py
simfire/world/_tests/test_cfd_wind.py
simfire/world/_tests/test_elevation_functions.py
simfire/world/_tests/test_rothermel.py
simfire/world/_tests/test_wind.py
simfire/world/elevation_functions.py
simfire/world/fuel_array_functions.py
simfire/world/parameters.py
simfire/world/presets.py
simfire-2.0.1.dist-info/LICENSE
simfire-2.0.1.dist-info/METADATA
simfire-2.0.1.dist-info/WHEEL
simfire-2.0.1.dist-info/RECORD
