Metadata-Version: 2.1
Name: simfire
Version: 2.0.1
Summary: Fire simulator built in Python
Home-page: https://github.com/mitrefireline/simfire
Keywords: python,reinforcement learning,simulation,fire
Author: Tim Welsh
Author-email: twelsh@mitre.org
Requires-Python: >=3.9,<3.10
Classifier: Programming Language :: Python :: 3
Classifier: Programming Language :: Python :: 3.9
Requires-Dist: Pillow (>=9.1.1,<11.0.0)
Requires-Dist: PyYAML (>=6.0,<7.0)
Requires-Dist: geopandas (>=0.14.4,<0.15.0)
Requires-Dist: geopy (>=2.4.1,<3.0.0)
Requires-Dist: geotiff (>=0.2.10,<0.3.0)
Requires-Dist: h5py (>=3.7.0,<4.0.0)
Requires-Dist: imagecodecs (>=2023.7.10,<2024.0.0)
Requires-Dist: jsonlines (>=3.1.0,<4.0.0)
Requires-Dist: landfire (>=0.5.0,<0.6.0)
Requires-Dist: matplotlib (>=3.5.2,<4.0.0)
Requires-Dist: noise (>=1.2.2,<2.0.0)
Requires-Dist: numpy (>=1.22.4,<2.0.0)
Requires-Dist: opencv-python (>=4.7.0.72,<5.0.0.0)
Requires-Dist: pygame (>=2.1.2,<3.0.0)
Requires-Dist: reportlab (>=3.6.10,<4.0.0)
Requires-Dist: rich (>=12.5.1,<13.0.0)
Requires-Dist: scikit-image (>=0.19.3,<0.20.0)
Requires-Dist: svglib (>=1.3.0,<2.0.0)
Requires-Dist: wurlitzer (>=3.0.2,<4.0.0)
Project-URL: Documentation, https://mitrefireline.github.io/simfire/
Project-URL: Repository, https://github.com/mitrefireline/simfire
